hf/fastapi/__init__.py
hf/fastapi/_app.py
hf/fastapi/_handlers.py
hf_py_fastapi-0.3.2.dist-info/METADATA
hf_py_fastapi-0.3.2.dist-info/WHEEL
hf_py_fastapi-0.3.2.dist-info/RECORD
