Metadata-Version: 2.3
Name: hf-py-fastapi
Version: 0.3.2
Summary: 
Author: kuanysh-beisembayev
Author-email: kuanysh.beisembayev@gmail.com
Requires-Python: >=3.12,<4.0
Classifier: Programming Language :: Python :: 3
Classifier: Programming Language :: Python :: 3.12
Classifier: Programming Language :: Python :: 3.13
Requires-Dist: fastapi[standard] (>=0.116.1,<0.117.0)
Requires-Dist: hf-py-base (==0.2.*)
